README.md
setup.py
dhooks/__init__.py
dhooks/client.py
dhooks/embed.py
dhooks/file.py
dhooks/utils.py
dhooks.egg-info/PKG-INFO
dhooks.egg-info/SOURCES.txt
dhooks.egg-info/dependency_links.txt
dhooks.egg-info/requires.txt
dhooks.egg-info/top_level.txt
test/test.py